<?xml version="1.0" encoding="UTF-8"?>
<launch4jConfig>
  <dontWrapJar>false</dontWrapJar>
  <headerType>console</headerType>
  <jar>D:\code\BinPacker\bin\BinPacker.jar</jar>
  <outfile>d:\code\BinPacker\bin\BinPacker.exe</outfile>
  <errTitle></errTitle>
  <cmdLine></cmdLine>
  <chdir>.</chdir>
  <priority>normal</priority>
  <downloadUrl>http://java.com/download</downloadUrl>
  <supportUrl></supportUrl>
  <stayAlive>false</stayAlive>
  <restartOnCrash>false</restartOnCrash>
  <manifest></manifest>
  <icon></icon>
  <jre>
    <path>c:\Program Files\Java\jre1.8.0_66</path>
    <bundledJre64Bit>false</bundledJre64Bit>
    <bundledJreAsFallback>false</bundledJreAsFallback>
    <minVersion>1.8.0</minVersion>
    <maxVersion>1.8.0_66</maxVersion>
    <jdkPreference>preferJre</jdkPreference>
    <runtimeBits>64/32</runtimeBits>
    <initialHeapSize>32</initialHeapSize>
    <maxHeapSize>1024</maxHeapSize>
  </jre>
</launch4jConfig>